<?xml version='1.0'?>
<island simulinkPath='dummy_beamformer/ch_sum' topLevelEntity='dummy_beamformer_ch_sum'>
    <port name='clk' dir='in' role='clock'/>
    <port name='areset' dir='in' clock='clk' role='resetHigh'/>
    <port name='d' clock='clk' reset='areset' width='32' dir='in' role='data' qsys_role='data_d' stm='dummy_beamformer/dummy_beamformer_ch_sum_AStInput_ChannelIn.stm' highLevelName='d' highLevelIndex='1' vector='0' complex='0'/>
    <port name='v' clock='clk' reset='areset' width='1' dir='in' role='valid' qsys_role='valid_v' stm='dummy_beamformer/dummy_beamformer_ch_sum_AStInput_ChannelIn.stm' highLevelName='v' highLevelIndex='2' vector='0' complex='0'/>
    <port name='c' clock='clk' reset='areset' width='8' dir='in' role='channel' qsys_role='channel_c' stm='dummy_beamformer/dummy_beamformer_ch_sum_AStInput_ChannelIn.stm' highLevelName='c' highLevelIndex='3' vector='0' complex='0'/>
    <port name='dout' clock='clk' reset='areset' width='32' dir='out' role='data' qsys_role='data_dout' stm='dummy_beamformer/dummy_beamformer_ch_sum_AStOutput_ChannelOut.stm' highLevelName='dout' highLevelIndex='1' vector='0' complex='0'/>
    <port name='vout' clock='clk' reset='areset' width='1' dir='out' role='valid' qsys_role='valid_vout' stm='dummy_beamformer/dummy_beamformer_ch_sum_AStOutput_ChannelOut.stm' highLevelName='vout' highLevelIndex='2' vector='0' complex='0'/>
    <port name='cout' clock='clk' reset='areset' width='8' dir='out' role='channel' qsys_role='channel_cout' stm='dummy_beamformer/dummy_beamformer_ch_sum_AStOutput_ChannelOut.stm' highLevelName='cout' highLevelIndex='3' vector='0' complex='0'/>
    <file path='eda/sim_lib/altera_primitives_components.vhd' base='quartus' type='vhdl' usage='simOnly' lib='altera'/>
    <file path='eda/sim_lib/altera_mf_components.vhd' base='quartus' type='vhdl' usage='simOnly' lib='altera_mf'/>
    <file path='eda/sim_lib/altera_mf.vhd' base='quartus' type='vhdl' usage='simOnly' lib='altera_mf'/>
    <file path='eda/sim_lib/220pack.vhd' base='quartus' type='vhdl' usage='simOnly' lib='lpm'/>
    <file path='eda/sim_lib/220model.vhd' base='quartus' type='vhdl' usage='simOnly' lib='lpm'/>
    <file path='eda/sim_lib/altera_lnsim_components.vhd' base='quartus' type='vhdl' usage='simOnly' lib='altera_lnsim'/>
    <file path='eda/sim_lib/altera_lnsim.sv' base='quartus' type='vhdl' usage='simOnly' lib='altera_lnsim'/>
    <file path='eda/sim_lib/twentynm_atoms.vhd' base='quartus' type='vhdl' usage='simOnly' lib='twentynm'/>
    <file path='eda/sim_lib/twentynm_components.vhd' base='quartus' type='vhdl' usage='simOnly' lib='twentynm'/>
    <file path='eda/sim_lib/mentor/twentynm_atoms_ncrypt.v' base='quartus' type='vhdl' usage='simOnly' lib='twentynm'/>
    <file path='dummy_beamformer/dummy_beamformer_ch_sum.vhd' base='rtl' type='vhdl' usage='all'/>
    <file path='dspba/backend/Libraries/vhdl/base/dspba_library_package.vhd' base='quartus' type='vhdl' usage='all'/>
    <file path='dspba/backend/Libraries/vhdl/base/dspba_library.vhd' base='quartus' type='vhdl' usage='all'/>
    <file path='dummy_beamformer/dummy_beamformer_ch_sum_AStInput.vhd' base='rtl' type='vhdl' usage='all'/>
    <file path='dummy_beamformer/dummy_beamformer_ch_sum_AStOutput.vhd' base='rtl' type='vhdl' usage='all'/>
    <file path='dummy_beamformer/dummy_beamformer_ch_sum_ch_sum.vhd' base='rtl' type='vhdl' usage='all'/>

</island>
