[
 {
  "sid":"sm_DynamicCompression:5249",
  "className":"Simulink.Annotation",
  "icon":"sm_DynamicCompression_2332",
  "name":"Put in a check here if we make L/R channels have different tables",
  "label":"Put in a check here if we make L/R channels have different tables",
  "parent":"sm_DynamicCompression:434",
  "inspector":{
   "params":[
    "Text",
    "DropShadow",
    "Interpreter",
    "FontName",
    "FontWeight",
    "FontSize",
    "FontAngle",
    "ForegroundColor",
    "BackgroundColor",
    "HorizontalAlignment",
    "UseDisplayTextAsClickCallback",
    "ClickFcn"
   ],
   "values":[
    "Put in a check here if we make L/R channels have different tables",
    "off",
    "off",
    "auto",
    "auto",
    -1,
    "auto",
    "black",
    "white",
    "left",
    "off",
    ""
   ],
   "tabs":[
   ],
   "tabs_idx":[
   ]
  },
  "viewer":{
   "jshandler":"webview/handlers/ElementHandler"
  },
  "obj_viewer":[
  ],
  "finder":[
  ]
 },
 {
  "sid":"sm_DynamicCompression:437",
  "className":"Simulink.Outport",
  "icon":"sm_DynamicCompression_2333",
  "name":"Left_Data_Out  ",
  "label":"Left_Data_Out  ",
  "parent":"sm_DynamicCompression:434",
  "inspector":{
   "params":[
    "Port",
    "IconDisplay",
    "OutMin",
    "OutMax",
    "OutDataTypeStr",
    "LockScale",
    "Unit",
    "PortDimensions",
    "VarSizeSig",
    "SampleTime",
    "SignalType",
    "BusOutputAsStruct",
    "EnsureOutportIsVirtual",
    "InitialOutput",
    "MustResolveToSignalObject",
    "OutputWhenDisabled",
    "OutputWhenUnConnected",
    "OutputWhenUnconnectedValue",
    "SignalName",
    "SignalObject",
    "SourceOfInitialOutputValue",
    "StorageClass",
    "VectorParamsAs1DForOutWhenUnconnected"
   ],
   "values":[
    "1",
    "Port number",
    "[]",
    "[]",
    "Inherit: auto",
    "off",
    "inherit",
    "-1",
    "Inherit",
    "-1",
    "auto",
    "off",
    "off",
    "0",
    "off",
    "held",
    "off",
    "0",
    "",
    [
    ],
    "Dialog",
    "Auto",
    "off"
   ],
   "tabs":[
    "Main",
    "Signal Attributes",
    "-Other"
   ],
   "tabs_idx":[
    0,
    2,
    11
   ]
  },
  "viewer":{
   "jshandler":"webview/handlers/ElementHandler"
  },
  "obj_viewer":[
  ],
  "finder":{
   "blocktype":"Outport",
   "masktype":""
  }
 },
 {
  "sid":"sm_DynamicCompression:435",
  "className":"Simulink.Inport",
  "icon":"sm_DynamicCompression_2333",
  "name":"Left_Data_In",
  "label":"Left_Data_In",
  "parent":"sm_DynamicCompression:434",
  "inspector":{
   "params":[
    "Port",
    "IconDisplay",
    "LatchByDelayingOutsideSignal",
    "LatchInputForFeedbackSignals",
    "OutputFunctionCall",
    "OutMin",
    "OutMax",
    "OutDataTypeStr",
    "LockScale",
    "Unit",
    "PortDimensions",
    "VarSizeSig",
    "SampleTime",
    "SignalType",
    "BusOutputAsStruct",
    "InputConnect",
    "Interpolate"
   ],
   "values":[
    "1",
    "Port number",
    "off",
    "off",
    "off",
    "[]",
    "[]",
    "Inherit: auto",
    "off",
    "inherit",
    "-1",
    "Inherit",
    "-1",
    "auto",
    "off",
    "",
    "on"
   ],
   "tabs":[
    "Main",
    "Signal Attributes",
    "-Other"
   ],
   "tabs_idx":[
    0,
    4,
    14
   ]
  },
  "viewer":{
   "jshandler":"webview/handlers/ElementHandler"
  },
  "obj_viewer":[
  ],
  "finder":{
   "blocktype":"Inport",
   "masktype":""
  }
 },
 {
  "sid":"sm_DynamicCompression:1013",
  "className":"Simulink.Inport",
  "icon":"sm_DynamicCompression_2333",
  "name":"Register_System_Enable",
  "label":"Register_System_Enable",
  "parent":"sm_DynamicCompression:434",
  "inspector":{
   "params":[
    "Port",
    "IconDisplay",
    "LatchByDelayingOutsideSignal",
    "LatchInputForFeedbackSignals",
    "OutputFunctionCall",
    "OutMin",
    "OutMax",
    "OutDataTypeStr",
    "LockScale",
    "Unit",
    "PortDimensions",
    "VarSizeSig",
    "SampleTime",
    "SignalType",
    "BusOutputAsStruct",
    "InputConnect",
    "Interpolate"
   ],
   "values":[
    "2",
    "Port number",
    "off",
    "off",
    "off",
    "[]",
    "[]",
    "Inherit: auto",
    "off",
    "inherit",
    "-1",
    "Inherit",
    "-1",
    "auto",
    "off",
    "",
    "on"
   ],
   "tabs":[
    "Main",
    "Signal Attributes",
    "-Other"
   ],
   "tabs_idx":[
    0,
    4,
    14
   ]
  },
  "viewer":{
   "jshandler":"webview/handlers/ElementHandler"
  },
  "obj_viewer":[
  ],
  "finder":{
   "blocktype":"Inport",
   "masktype":""
  }
 },
 {
  "sid":"sm_DynamicCompression:1047",
  "className":"Simulink.SubSystem",
  "icon":"sm_DynamicCompression_2331",
  "name":"recalculate",
  "label":"recalculate",
  "parent":"sm_DynamicCompression:434",
  "inspector":{
   "params":[
    "ShowPortLabels",
    "Permissions",
    "ErrorFcn",
    "PermitHierarchicalResolution",
    "TreatAsAtomicUnit",
    "MinAlgLoopOccurrences",
    "SystemSampleTime",
    "TreatAsGroupedWhenPropagatingVariantConditions",
    "RTWSystemCode",
    "ReferencedSubsystem",
    "AllowZeroVariantControls",
    "AutoFrameSizeCalculation",
    "BlockChoice",
    "CompiledActiveChoiceBlock",
    "CompiledActiveChoiceControl",
    "ExecutionDomainType",
    "FunctionInterfaceSpec",
    "FunctionWithSeparateData",
    "GeneratePreprocessorConditionals",
    "IsSubsystemVirtual",
    "LabelModeActiveChoice",
    "Latency",
    "MemberBlocks",
    "PartitionName",
    "PropExecContextOutsideSubsystem",
    "PropagateVariantConditions",
    "RTWFcnName",
    "RTWFcnNameOpts",
    "RTWFileName",
    "RTWFileNameOpts",
    "RTWMemSecDataConstants",
    "RTWMemSecDataInternal",
    "RTWMemSecDataParameters",
    "RTWMemSecFuncExecute",
    "RTWMemSecFuncInitTerm",
    "ScheduleAs",
    "SetExecutionDomain",
    "TemplateBlock",
    "Variant",
    "VariantControl",
    "VariantControlMode"
   ],
   "values":[
    "FromPortIcon",
    "ReadWrite",
    "",
    "All",
    "off",
    "off",
    "-1",
    "on",
    "Auto",
    "",
    "off",
    "off",
    "",
    "",
    "",
    "Deduce",
    "void_void",
    "off",
    "off",
    "on",
    "",
    "0",
    "",
    "",
    "off",
    "off",
    "",
    "Auto",
    "",
    "Auto",
    "Inherit from model",
    "Inherit from model",
    "Inherit from model",
    "Inherit from model",
    "Inherit from model",
    "Sample time",
    "off",
    "",
    "off",
    "",
    "Expression"
   ],
   "tabs":[
    "Main",
    "Code Generation",
    "Subsystem Reference",
    "-Other"
   ],
   "tabs_idx":[
    0,
    8,
    9,
    10
   ]
  },
  "viewer":{
   "jshandler":"webview/handlers/ContainerHandler"
  },
  "obj_viewer":[
  ],
  "finder":{
   "blocktype":"SubSystem",
   "masktype":""
  }
 },
 {
  "sid":"sm_DynamicCompression:1042",
  "className":"Simulink.FromWorkspace",
  "icon":"sm_DynamicCompression_2333",
  "name":"From Workspace",
  "label":"From Workspace",
  "parent":"sm_DynamicCompression:434",
  "inspector":{
   "params":[
    "VariableName",
    "OutDataTypeStr",
    "SampleTime",
    "Interpolate",
    "ZeroCross",
    "OutputAfterFinalValue"
   ],
   "values":[
    "sig_in",
    "Inherit: auto",
    "Ts",
    "on",
    "on",
    "Setting to zero"
   ],
   "tabs":[
    "Parameter Attributes"
   ],
   "tabs_idx":0
  },
  "viewer":{
   "jshandler":"webview/handlers/ElementHandler"
  },
  "obj_viewer":[
  ],
  "finder":{
   "blocktype":"FromWorkspace",
   "masktype":""
  }
 },
 {
  "sid":"sm_DynamicCompression:1046",
  "className":"Simulink.ToWorkspace",
  "icon":"sm_DynamicCompression_2333",
  "name":"To Workspace",
  "label":"To Workspace",
  "parent":"sm_DynamicCompression:434",
  "inspector":{
   "params":[
    "VariableName",
    "MaxDataPoints",
    "Decimation",
    "SaveFormat",
    "FixptAsFi",
    "SampleTime",
    "Save2DSignal"
   ],
   "values":[
    "proc_sig",
    "inf",
    "1",
    "Timeseries",
    "on",
    "-1",
    "3-D array (concatenate along third dimension)"
   ],
   "tabs":[
    "Parameter Attributes",
    "-Other"
   ],
   "tabs_idx":[
    0,
    6
   ]
  },
  "viewer":{
   "jshandler":"webview/handlers/ElementHandler"
  },
  "obj_viewer":[
  ],
  "finder":{
   "blocktype":"ToWorkspace",
   "masktype":""
  }
 },
 {
  "sid":"sm_DynamicCompression:1043",
  "className":"Simulink.FromWorkspace",
  "icon":"sm_DynamicCompression_2333",
  "name":"From Workspace1",
  "label":"From Workspace1",
  "parent":"sm_DynamicCompression:434",
  "inspector":{
   "params":[
    "VariableName",
    "OutDataTypeStr",
    "SampleTime",
    "Interpolate",
    "ZeroCross",
    "OutputAfterFinalValue"
   ],
   "values":[
    "Table_Fill_t",
    "Inherit: auto",
    "Ts",
    "off",
    "on",
    "Setting to zero"
   ],
   "tabs":[
    "Parameter Attributes"
   ],
   "tabs_idx":0
  },
  "viewer":{
   "jshandler":"webview/handlers/ElementHandler"
  },
  "obj_viewer":[
  ],
  "finder":{
   "blocktype":"FromWorkspace",
   "masktype":""
  }
 },
 {
  "sid":"sm_DynamicCompression:1044",
  "className":"Simulink.FromWorkspace",
  "icon":"sm_DynamicCompression_2333",
  "name":"From Workspace2",
  "label":"From Workspace2",
  "parent":"sm_DynamicCompression:434",
  "inspector":{
   "params":[
    "VariableName",
    "OutDataTypeStr",
    "SampleTime",
    "Interpolate",
    "ZeroCross",
    "OutputAfterFinalValue"
   ],
   "values":[
    "Fill_Valid_t",
    "Inherit: auto",
    "Ts",
    "on",
    "on",
    "Setting to zero"
   ],
   "tabs":[
    "Parameter Attributes"
   ],
   "tabs_idx":0
  },
  "viewer":{
   "jshandler":"webview/handlers/ElementHandler"
  },
  "obj_viewer":[
  ],
  "finder":{
   "blocktype":"FromWorkspace",
   "masktype":""
  }
 },
 {
  "sid":"sm_DynamicCompression:1045",
  "className":"Simulink.FromWorkspace",
  "icon":"sm_DynamicCompression_2333",
  "name":"From Workspace4",
  "label":"From Workspace4",
  "parent":"sm_DynamicCompression:434",
  "inspector":{
   "params":[
    "VariableName",
    "OutDataTypeStr",
    "SampleTime",
    "Interpolate",
    "ZeroCross",
    "OutputAfterFinalValue"
   ],
   "values":[
    "Reset",
    "Inherit: auto",
    "Ts",
    "off",
    "on",
    "Setting to zero"
   ],
   "tabs":[
    "Parameter Attributes"
   ],
   "tabs_idx":0
  },
  "viewer":{
   "jshandler":"webview/handlers/ElementHandler"
  },
  "obj_viewer":[
  ],
  "finder":{
   "blocktype":"FromWorkspace",
   "masktype":""
  }
 },
 {
  "sid":"sm_DynamicCompression:1038",
  "className":"Simulink.DataTypeConversion",
  "icon":"sm_DynamicCompression_2333",
  "name":"Cast To Boolean",
  "label":"Cast To Boolean",
  "parent":"sm_DynamicCompression:434",
  "inspector":{
   "params":[
    "OutMin",
    "OutMax",
    "OutDataTypeStr",
    "LockScale",
    "ConvertRealWorld",
    "RndMeth",
    "SaturateOnIntegerOverflow",
    "SampleTime"
   ],
   "values":[
    "[]",
    "[]",
    "boolean",
    "off",
    "Real World Value (RWV)",
    "Floor",
    "off",
    "-1"
   ],
   "tabs":[
    "Parameter Attributes",
    "-Other"
   ],
   "tabs_idx":[
    0,
    7
   ]
  },
  "viewer":{
   "jshandler":"webview/handlers/ElementHandler"
  },
  "obj_viewer":[
  ],
  "finder":{
   "blocktype":"DataTypeConversion",
   "masktype":""
  }
 },
 {
  "sid":"sm_DynamicCompression:1039",
  "className":"Simulink.DataTypeConversion",
  "icon":"sm_DynamicCompression_2333",
  "name":"Cast To Boolean1",
  "label":"Cast To Boolean1",
  "parent":"sm_DynamicCompression:434",
  "inspector":{
   "params":[
    "OutMin",
    "OutMax",
    "OutDataTypeStr",
    "LockScale",
    "ConvertRealWorld",
    "RndMeth",
    "SaturateOnIntegerOverflow",
    "SampleTime"
   ],
   "values":[
    "[]",
    "[]",
    "boolean",
    "off",
    "Real World Value (RWV)",
    "Floor",
    "off",
    "-1"
   ],
   "tabs":[
    "Parameter Attributes",
    "-Other"
   ],
   "tabs_idx":[
    0,
    7
   ]
  },
  "viewer":{
   "jshandler":"webview/handlers/ElementHandler"
  },
  "obj_viewer":[
  ],
  "finder":{
   "blocktype":"DataTypeConversion",
   "masktype":""
  }
 },
 {
  "sid":"sm_DynamicCompression:1040",
  "className":"Simulink.DataTypeConversion",
  "icon":"sm_DynamicCompression_2333",
  "name":"Cast To fp(1,32,28)",
  "label":"Cast To fp(1,32,28)",
  "parent":"sm_DynamicCompression:434",
  "inspector":{
   "params":[
    "OutMin",
    "OutMax",
    "OutDataTypeStr",
    "LockScale",
    "ConvertRealWorld",
    "RndMeth",
    "SaturateOnIntegerOverflow",
    "SampleTime"
   ],
   "values":[
    "[]",
    "[]",
    "fixdt(1,32,28)",
    "off",
    "Real World Value (RWV)",
    "Round",
    "off",
    "-1"
   ],
   "tabs":[
    "Parameter Attributes",
    "-Other"
   ],
   "tabs_idx":[
    0,
    7
   ]
  },
  "viewer":{
   "jshandler":"webview/handlers/ElementHandler"
  },
  "obj_viewer":[
  ],
  "finder":{
   "blocktype":"DataTypeConversion",
   "masktype":""
  }
 },
 {
  "sid":"sm_DynamicCompression:1041",
  "className":"Simulink.DataTypeConversion",
  "icon":"sm_DynamicCompression_2333",
  "name":"Cast To fp(1,32,28)1",
  "label":"Cast To fp(1,32,28)1",
  "parent":"sm_DynamicCompression:434",
  "inspector":{
   "params":[
    "OutMin",
    "OutMax",
    "OutDataTypeStr",
    "LockScale",
    "ConvertRealWorld",
    "RndMeth",
    "SaturateOnIntegerOverflow",
    "SampleTime"
   ],
   "values":[
    "[]",
    "[]",
    "fixdt(1,32,28)",
    "off",
    "Real World Value (RWV)",
    "Round",
    "off",
    "-1"
   ],
   "tabs":[
    "Parameter Attributes",
    "-Other"
   ],
   "tabs_idx":[
    0,
    7
   ]
  },
  "viewer":{
   "jshandler":"webview/handlers/ElementHandler"
  },
  "obj_viewer":[
  ],
  "finder":{
   "blocktype":"DataTypeConversion",
   "masktype":""
  }
 },
 {
  "sid":"sm_DynamicCompression:2973",
  "className":"Simulink.Terminator",
  "icon":"sm_DynamicCompression_2333",
  "name":"Terminator",
  "label":"Terminator",
  "parent":"sm_DynamicCompression:434",
  "inspector":{
   "params":[
   ],
   "values":[
   ],
   "tabs":[
   ],
   "tabs_idx":[
   ]
  },
  "viewer":{
   "jshandler":"webview/handlers/ElementHandler"
  },
  "obj_viewer":[
  ],
  "finder":{
   "blocktype":"Terminator",
   "masktype":""
  }
 },
 {
  "sid":"sm_DynamicCompression:4277",
  "className":"Simulink.Terminator",
  "icon":"sm_DynamicCompression_2333",
  "name":"Terminator1",
  "label":"Terminator1",
  "parent":"sm_DynamicCompression:434",
  "inspector":{
   "params":[
   ],
   "values":[
   ],
   "tabs":[
   ],
   "tabs_idx":[
   ]
  },
  "viewer":{
   "jshandler":"webview/handlers/ElementHandler"
  },
  "obj_viewer":[
  ],
  "finder":{
   "blocktype":"Terminator",
   "masktype":""
  }
 },
 {
  "sid":"sm_DynamicCompression:4279",
  "className":"Simulink.Terminator",
  "icon":"sm_DynamicCompression_2333",
  "name":"Terminator2",
  "label":"Terminator2",
  "parent":"sm_DynamicCompression:434",
  "inspector":{
   "params":[
   ],
   "values":[
   ],
   "tabs":[
   ],
   "tabs_idx":[
   ]
  },
  "viewer":{
   "jshandler":"webview/handlers/ElementHandler"
  },
  "obj_viewer":[
  ],
  "finder":{
   "blocktype":"Terminator",
   "masktype":""
  }
 },
 {
  "sid":"sm_DynamicCompression:4280",
  "className":"Simulink.Terminator",
  "icon":"sm_DynamicCompression_2333",
  "name":"Terminator3",
  "label":"Terminator3",
  "parent":"sm_DynamicCompression:434",
  "inspector":{
   "params":[
   ],
   "values":[
   ],
   "tabs":[
   ],
   "tabs_idx":[
   ]
  },
  "viewer":{
   "jshandler":"webview/handlers/ElementHandler"
  },
  "obj_viewer":[
  ],
  "finder":{
   "blocktype":"Terminator",
   "masktype":""
  }
 },
 {
  "sid":"sm_DynamicCompression:4282",
  "className":"Simulink.Constant",
  "icon":"sm_DynamicCompression_2333",
  "name":"Constant2",
  "label":"Constant2",
  "parent":"sm_DynamicCompression:434",
  "inspector":{
   "params":[
    "Value",
    "VectorParams1D",
    "SampleTime",
    "OutMin",
    "OutMax",
    "OutDataTypeStr",
    "LockScale",
    "FramePeriod"
   ],
   "values":[
    "0",
    "on",
    "-1",
    "[]",
    "[]",
    "boolean",
    "off",
    "inf"
   ],
   "tabs":[
    "Main",
    "Signal Attributes",
    "-Other"
   ],
   "tabs_idx":[
    0,
    3,
    7
   ]
  },
  "viewer":{
   "jshandler":"webview/handlers/ElementHandler"
  },
  "obj_viewer":[
  ],
  "finder":{
   "blocktype":"Constant",
   "masktype":""
  }
 },
 {
  "sid":"sm_DynamicCompression:5248",
  "className":"Simulink.Inport",
  "icon":"sm_DynamicCompression_2333",
  "name":"Register_Preset_Sel",
  "label":"Register_Preset_Sel",
  "parent":"sm_DynamicCompression:434",
  "inspector":{
   "params":[
    "Port",
    "IconDisplay",
    "LatchByDelayingOutsideSignal",
    "LatchInputForFeedbackSignals",
    "OutputFunctionCall",
    "OutMin",
    "OutMax",
    "OutDataTypeStr",
    "LockScale",
    "Unit",
    "PortDimensions",
    "VarSizeSig",
    "SampleTime",
    "SignalType",
    "BusOutputAsStruct",
    "InputConnect",
    "Interpolate"
   ],
   "values":[
    "3",
    "Port number",
    "off",
    "off",
    "off",
    "[]",
    "[]",
    "Inherit: auto",
    "off",
    "inherit",
    "-1",
    "Inherit",
    "-1",
    "auto",
    "off",
    "",
    "on"
   ],
   "tabs":[
    "Main",
    "Signal Attributes",
    "-Other"
   ],
   "tabs_idx":[
    0,
    4,
    14
   ]
  },
  "viewer":{
   "jshandler":"webview/handlers/ElementHandler"
  },
  "obj_viewer":[
  ],
  "finder":{
   "blocktype":"Inport",
   "masktype":""
  }
 },
 {
  "sid":"sm_DynamicCompression:5324",
  "className":"Simulink.Inport",
  "icon":"sm_DynamicCompression_2333",
  "name":"Valid_in",
  "label":"Valid_in",
  "parent":"sm_DynamicCompression:434",
  "inspector":{
   "params":[
    "Port",
    "IconDisplay",
    "LatchByDelayingOutsideSignal",
    "LatchInputForFeedbackSignals",
    "OutputFunctionCall",
    "OutMin",
    "OutMax",
    "OutDataTypeStr",
    "LockScale",
    "Unit",
    "PortDimensions",
    "VarSizeSig",
    "SampleTime",
    "SignalType",
    "BusOutputAsStruct",
    "InputConnect",
    "Interpolate"
   ],
   "values":[
    "4",
    "Port number",
    "off",
    "off",
    "off",
    "[]",
    "[]",
    "Inherit: auto",
    "off",
    "inherit",
    "-1",
    "Inherit",
    "-1",
    "auto",
    "off",
    "",
    "on"
   ],
   "tabs":[
    "Main",
    "Signal Attributes",
    "-Other"
   ],
   "tabs_idx":[
    0,
    4,
    14
   ]
  },
  "viewer":{
   "jshandler":"webview/handlers/ElementHandler"
  },
  "obj_viewer":[
  ],
  "finder":{
   "blocktype":"Inport",
   "masktype":""
  }
 },
 {
  "sid":"sm_DynamicCompression:5559",
  "className":"Simulink.Switch",
  "icon":"sm_DynamicCompression_2333",
  "name":"Switch",
  "label":"Switch",
  "parent":"sm_DynamicCompression:434",
  "inspector":{
   "params":[
    "Criteria",
    "Threshold",
    "ZeroCross",
    "InputSameDT",
    "OutMin",
    "OutMax",
    "OutDataTypeStr",
    "LockScale",
    "RndMeth",
    "SaturateOnIntegerOverflow",
    "AllowDiffInputSizes",
    "SampleTime"
   ],
   "values":[
    "u2 ~= 0",
    "0",
    "on",
    "off",
    "[]",
    "[]",
    "Inherit: Inherit via internal rule",
    "off",
    "Floor",
    "off",
    "off",
    "-1"
   ],
   "tabs":[
    "Main",
    "Signal Attributes",
    "-Other"
   ],
   "tabs_idx":[
    0,
    3,
    11
   ]
  },
  "viewer":{
   "jshandler":"webview/handlers/ElementHandler"
  },
  "obj_viewer":[
  ],
  "finder":{
   "blocktype":"Switch",
   "masktype":""
  }
 },
 {
  "sid":"sm_DynamicCompression:6567",
  "className":"Simulink.DataTypeConversion",
  "icon":"sm_DynamicCompression_2333",
  "name":"Data Type Conversion",
  "label":"Data Type Conversion",
  "parent":"sm_DynamicCompression:434",
  "inspector":{
   "params":[
    "OutMin",
    "OutMax",
    "OutDataTypeStr",
    "LockScale",
    "ConvertRealWorld",
    "RndMeth",
    "SaturateOnIntegerOverflow",
    "SampleTime"
   ],
   "values":[
    "[]",
    "[]",
    "boolean",
    "off",
    "Real World Value (RWV)",
    "Floor",
    "off",
    "-1"
   ],
   "tabs":[
    "Parameter Attributes",
    "-Other"
   ],
   "tabs_idx":[
    0,
    7
   ]
  },
  "viewer":{
   "jshandler":"webview/handlers/ElementHandler"
  },
  "obj_viewer":[
  ],
  "finder":{
   "blocktype":"DataTypeConversion",
   "masktype":""
  }
 },
 {
  "sid":"sm_DynamicCompression:1043#out:1",
  "className":"Simulink.Line",
  "icon":"sm_DynamicCompression_2334",
  "name":"Table_Values",
  "label":"Table_Values",
  "parent":"sm_DynamicCompression:434",
  "inspector":{
   "params":[
    "SignalNameFromLabel",
    "MustResolveToSignal",
    "ShowPropagatedSignal",
    "DataLogging",
    "TestPoint",
    "SignalObjectPackage",
    "StorageClass",
    "Description",
    "documentLink"
   ],
   "values":[
    "Table_Values",
    "off",
    "off",
    "on",
    "off",
    "Simulink",
    "Auto",
    "",
    ""
   ],
   "tabs":[
    "Parameter Attributes",
    "Logging and Accessibility",
    "Code Generation",
    "Documentation"
   ],
   "tabs_idx":[
    0,
    3,
    5,
    7
   ]
  },
  "viewer":{
   "jshandler":"webview/handlers/ElementHandler"
  },
  "obj_viewer":[
  ],
  "finder":[
  ]
 },
 {
  "sid":"sm_DynamicCompression:1044#out:1",
  "className":"Simulink.Line",
  "icon":"sm_DynamicCompression_2334",
  "name":"",
  "label":"",
  "parent":"sm_DynamicCompression:434",
  "inspector":{
   "params":[
    "SignalNameFromLabel",
    "MustResolveToSignal",
    "ShowPropagatedSignal",
    "DataLogging",
    "TestPoint",
    "SignalObjectPackage",
    "StorageClass",
    "Description",
    "documentLink"
   ],
   "values":[
    "",
    "off",
    "off",
    "on",
    "off",
    "Simulink",
    "Auto",
    "",
    ""
   ],
   "tabs":[
    "Parameter Attributes",
    "Logging and Accessibility",
    "Code Generation",
    "Documentation"
   ],
   "tabs_idx":[
    0,
    3,
    5,
    7
   ]
  },
  "viewer":{
   "jshandler":"webview/handlers/ElementHandler"
  },
  "obj_viewer":[
  ],
  "finder":[
  ]
 },
 {
  "sid":"sm_DynamicCompression:1042#out:1",
  "className":"Simulink.Line",
  "icon":"sm_DynamicCompression_2334",
  "name":"",
  "label":"",
  "parent":"sm_DynamicCompression:434",
  "inspector":{
   "params":[
    "SignalNameFromLabel",
    "MustResolveToSignal",
    "ShowPropagatedSignal",
    "DataLogging",
    "TestPoint",
    "SignalObjectPackage",
    "StorageClass",
    "Description",
    "documentLink"
   ],
   "values":[
    "",
    "off",
    "off",
    "on",
    "off",
    "Simulink",
    "Auto",
    "",
    ""
   ],
   "tabs":[
    "Parameter Attributes",
    "Logging and Accessibility",
    "Code Generation",
    "Documentation"
   ],
   "tabs_idx":[
    0,
    3,
    5,
    7
   ]
  },
  "viewer":{
   "jshandler":"webview/handlers/ElementHandler"
  },
  "obj_viewer":[
  ],
  "finder":[
  ]
 },
 {
  "sid":"sm_DynamicCompression:1045#out:1",
  "className":"Simulink.Line",
  "icon":"sm_DynamicCompression_2334",
  "name":"",
  "label":"",
  "parent":"sm_DynamicCompression:434",
  "inspector":{
   "params":[
    "SignalNameFromLabel",
    "MustResolveToSignal",
    "ShowPropagatedSignal",
    "DataLogging",
    "TestPoint",
    "SignalObjectPackage",
    "StorageClass",
    "Description",
    "documentLink"
   ],
   "values":[
    "",
    "off",
    "off",
    "off",
    "off",
    "Simulink",
    "Auto",
    "",
    ""
   ],
   "tabs":[
    "Parameter Attributes",
    "Logging and Accessibility",
    "Code Generation",
    "Documentation"
   ],
   "tabs_idx":[
    0,
    3,
    5,
    7
   ]
  },
  "viewer":{
   "jshandler":"webview/handlers/ElementHandler"
  },
  "obj_viewer":[
  ],
  "finder":[
  ]
 },
 {
  "sid":"sm_DynamicCompression:435#out:1",
  "className":"Simulink.Line",
  "icon":"sm_DynamicCompression_2334",
  "name":"",
  "label":"",
  "parent":"sm_DynamicCompression:434",
  "inspector":{
   "params":[
    "SignalNameFromLabel",
    "MustResolveToSignal",
    "ShowPropagatedSignal",
    "DataLogging",
    "TestPoint",
    "SignalObjectPackage",
    "StorageClass",
    "Description",
    "documentLink"
   ],
   "values":[
    "",
    "off",
    "off",
    "off",
    "off",
    "Simulink",
    "Auto",
    "",
    ""
   ],
   "tabs":[
    "Parameter Attributes",
    "Logging and Accessibility",
    "Code Generation",
    "Documentation"
   ],
   "tabs_idx":[
    0,
    3,
    5,
    7
   ]
  },
  "viewer":{
   "jshandler":"webview/handlers/ElementHandler"
  },
  "obj_viewer":[
  ],
  "finder":[
  ]
 },
 {
  "sid":"sm_DynamicCompression:1041#out:1",
  "className":"Simulink.Line",
  "icon":"sm_DynamicCompression_2334",
  "name":"",
  "label":"",
  "parent":"sm_DynamicCompression:434",
  "inspector":{
   "params":[
    "SignalNameFromLabel",
    "MustResolveToSignal",
    "ShowPropagatedSignal",
    "DataLogging",
    "TestPoint",
    "SignalObjectPackage",
    "StorageClass",
    "Description",
    "documentLink"
   ],
   "values":[
    "",
    "off",
    "off",
    "off",
    "off",
    "Simulink",
    "Auto",
    "",
    ""
   ],
   "tabs":[
    "Parameter Attributes",
    "Logging and Accessibility",
    "Code Generation",
    "Documentation"
   ],
   "tabs_idx":[
    0,
    3,
    5,
    7
   ]
  },
  "viewer":{
   "jshandler":"webview/handlers/ElementHandler"
  },
  "obj_viewer":[
  ],
  "finder":[
  ]
 },
 {
  "sid":"sm_DynamicCompression:1040#out:1",
  "className":"Simulink.Line",
  "icon":"sm_DynamicCompression_2334",
  "name":"",
  "label":"",
  "parent":"sm_DynamicCompression:434",
  "inspector":{
   "params":[
    "SignalNameFromLabel",
    "MustResolveToSignal",
    "ShowPropagatedSignal",
    "DataLogging",
    "TestPoint",
    "SignalObjectPackage",
    "StorageClass",
    "Description",
    "documentLink"
   ],
   "values":[
    "",
    "off",
    "off",
    "off",
    "off",
    "Simulink",
    "Auto",
    "",
    ""
   ],
   "tabs":[
    "Parameter Attributes",
    "Logging and Accessibility",
    "Code Generation",
    "Documentation"
   ],
   "tabs_idx":[
    0,
    3,
    5,
    7
   ]
  },
  "viewer":{
   "jshandler":"webview/handlers/ElementHandler"
  },
  "obj_viewer":[
  ],
  "finder":[
  ]
 },
 {
  "sid":"sm_DynamicCompression:1038#out:1",
  "className":"Simulink.Line",
  "icon":"sm_DynamicCompression_2334",
  "name":"",
  "label":"",
  "parent":"sm_DynamicCompression:434",
  "inspector":{
   "params":[
    "SignalNameFromLabel",
    "MustResolveToSignal",
    "ShowPropagatedSignal",
    "DataLogging",
    "TestPoint",
    "SignalObjectPackage",
    "StorageClass",
    "Description",
    "documentLink"
   ],
   "values":[
    "",
    "off",
    "off",
    "on",
    "off",
    "Simulink",
    "Auto",
    "",
    ""
   ],
   "tabs":[
    "Parameter Attributes",
    "Logging and Accessibility",
    "Code Generation",
    "Documentation"
   ],
   "tabs_idx":[
    0,
    3,
    5,
    7
   ]
  },
  "viewer":{
   "jshandler":"webview/handlers/ElementHandler"
  },
  "obj_viewer":[
  ],
  "finder":[
  ]
 },
 {
  "sid":"sm_DynamicCompression:1039#out:1",
  "className":"Simulink.Line",
  "icon":"sm_DynamicCompression_2334",
  "name":"",
  "label":"",
  "parent":"sm_DynamicCompression:434",
  "inspector":{
   "params":[
    "SignalNameFromLabel",
    "MustResolveToSignal",
    "ShowPropagatedSignal",
    "DataLogging",
    "TestPoint",
    "SignalObjectPackage",
    "StorageClass",
    "Description",
    "documentLink"
   ],
   "values":[
    "",
    "off",
    "off",
    "on",
    "off",
    "Simulink",
    "Auto",
    "",
    ""
   ],
   "tabs":[
    "Parameter Attributes",
    "Logging and Accessibility",
    "Code Generation",
    "Documentation"
   ],
   "tabs_idx":[
    0,
    3,
    5,
    7
   ]
  },
  "viewer":{
   "jshandler":"webview/handlers/ElementHandler"
  },
  "obj_viewer":[
  ],
  "finder":[
  ]
 },
 {
  "sid":"sm_DynamicCompression:4282#out:1",
  "className":"Simulink.Line",
  "icon":"sm_DynamicCompression_2334",
  "name":"",
  "label":"",
  "parent":"sm_DynamicCompression:434",
  "inspector":{
   "params":[
    "SignalNameFromLabel",
    "MustResolveToSignal",
    "ShowPropagatedSignal",
    "DataLogging",
    "TestPoint",
    "SignalObjectPackage",
    "StorageClass",
    "Description",
    "documentLink"
   ],
   "values":[
    "",
    "off",
    "off",
    "off",
    "off",
    "Simulink",
    "Auto",
    "",
    ""
   ],
   "tabs":[
    "Parameter Attributes",
    "Logging and Accessibility",
    "Code Generation",
    "Documentation"
   ],
   "tabs_idx":[
    0,
    3,
    5,
    7
   ]
  },
  "viewer":{
   "jshandler":"webview/handlers/ElementHandler"
  },
  "obj_viewer":[
  ],
  "finder":[
  ]
 },
 {
  "sid":"sm_DynamicCompression:1047#out:1",
  "className":"Simulink.Line",
  "icon":"sm_DynamicCompression_2334",
  "name":"",
  "label":"",
  "parent":"sm_DynamicCompression:434",
  "inspector":{
   "params":[
    "SignalNameFromLabel",
    "MustResolveToSignal",
    "ShowPropagatedSignal",
    "DataLogging",
    "TestPoint",
    "SignalObjectPackage",
    "StorageClass",
    "Description",
    "documentLink"
   ],
   "values":[
    "",
    "off",
    "off",
    "on",
    "off",
    "Simulink",
    "Auto",
    "",
    ""
   ],
   "tabs":[
    "Parameter Attributes",
    "Logging and Accessibility",
    "Code Generation",
    "Documentation"
   ],
   "tabs_idx":[
    0,
    3,
    5,
    7
   ]
  },
  "viewer":{
   "jshandler":"webview/handlers/ElementHandler"
  },
  "obj_viewer":[
  ],
  "finder":[
  ]
 },
 {
  "sid":"sm_DynamicCompression:1013#out:1",
  "className":"Simulink.Line",
  "icon":"sm_DynamicCompression_2334",
  "name":"",
  "label":"",
  "parent":"sm_DynamicCompression:434",
  "inspector":{
   "params":[
    "SignalNameFromLabel",
    "MustResolveToSignal",
    "ShowPropagatedSignal",
    "DataLogging",
    "TestPoint",
    "SignalObjectPackage",
    "StorageClass",
    "Description",
    "documentLink"
   ],
   "values":[
    "",
    "off",
    "off",
    "off",
    "off",
    "Simulink",
    "Auto",
    "",
    ""
   ],
   "tabs":[
    "Parameter Attributes",
    "Logging and Accessibility",
    "Code Generation",
    "Documentation"
   ],
   "tabs_idx":[
    0,
    3,
    5,
    7
   ]
  },
  "viewer":{
   "jshandler":"webview/handlers/ElementHandler"
  },
  "obj_viewer":[
  ],
  "finder":[
  ]
 },
 {
  "sid":"sm_DynamicCompression:5248#out:1",
  "className":"Simulink.Line",
  "icon":"sm_DynamicCompression_2334",
  "name":"",
  "label":"",
  "parent":"sm_DynamicCompression:434",
  "inspector":{
   "params":[
    "SignalNameFromLabel",
    "MustResolveToSignal",
    "ShowPropagatedSignal",
    "DataLogging",
    "TestPoint",
    "SignalObjectPackage",
    "StorageClass",
    "Description",
    "documentLink"
   ],
   "values":[
    "",
    "off",
    "off",
    "off",
    "off",
    "Simulink",
    "Auto",
    "",
    ""
   ],
   "tabs":[
    "Parameter Attributes",
    "Logging and Accessibility",
    "Code Generation",
    "Documentation"
   ],
   "tabs_idx":[
    0,
    3,
    5,
    7
   ]
  },
  "viewer":{
   "jshandler":"webview/handlers/ElementHandler"
  },
  "obj_viewer":[
  ],
  "finder":[
  ]
 },
 {
  "sid":"sm_DynamicCompression:5324#out:1",
  "className":"Simulink.Line",
  "icon":"sm_DynamicCompression_2334",
  "name":"",
  "label":"",
  "parent":"sm_DynamicCompression:434",
  "inspector":{
   "params":[
    "SignalNameFromLabel",
    "MustResolveToSignal",
    "ShowPropagatedSignal",
    "DataLogging",
    "TestPoint",
    "SignalObjectPackage",
    "StorageClass",
    "Description",
    "documentLink"
   ],
   "values":[
    "",
    "off",
    "off",
    "off",
    "off",
    "Simulink",
    "Auto",
    "",
    ""
   ],
   "tabs":[
    "Parameter Attributes",
    "Logging and Accessibility",
    "Code Generation",
    "Documentation"
   ],
   "tabs_idx":[
    0,
    3,
    5,
    7
   ]
  },
  "viewer":{
   "jshandler":"webview/handlers/ElementHandler"
  },
  "obj_viewer":[
  ],
  "finder":[
  ]
 },
 {
  "sid":"sm_DynamicCompression:5559#out:1",
  "className":"Simulink.Line",
  "icon":"sm_DynamicCompression_2334",
  "name":"",
  "label":"",
  "parent":"sm_DynamicCompression:434",
  "inspector":{
   "params":[
    "SignalNameFromLabel",
    "MustResolveToSignal",
    "ShowPropagatedSignal",
    "DataLogging",
    "TestPoint",
    "SignalObjectPackage",
    "StorageClass",
    "Description",
    "documentLink"
   ],
   "values":[
    "",
    "off",
    "off",
    "off",
    "off",
    "Simulink",
    "Auto",
    "",
    ""
   ],
   "tabs":[
    "Parameter Attributes",
    "Logging and Accessibility",
    "Code Generation",
    "Documentation"
   ],
   "tabs_idx":[
    0,
    3,
    5,
    7
   ]
  },
  "viewer":{
   "jshandler":"webview/handlers/ElementHandler"
  },
  "obj_viewer":[
  ],
  "finder":[
  ]
 },
 {
  "sid":"sm_DynamicCompression:6567#out:1",
  "className":"Simulink.Line",
  "icon":"sm_DynamicCompression_2334",
  "name":"",
  "label":"",
  "parent":"sm_DynamicCompression:434",
  "inspector":{
   "params":[
    "SignalNameFromLabel",
    "MustResolveToSignal",
    "ShowPropagatedSignal",
    "DataLogging",
    "TestPoint",
    "SignalObjectPackage",
    "StorageClass",
    "Description",
    "documentLink"
   ],
   "values":[
    "",
    "off",
    "off",
    "off",
    "off",
    "Simulink",
    "Auto",
    "",
    ""
   ],
   "tabs":[
    "Parameter Attributes",
    "Logging and Accessibility",
    "Code Generation",
    "Documentation"
   ],
   "tabs_idx":[
    0,
    3,
    5,
    7
   ]
  },
  "viewer":{
   "jshandler":"webview/handlers/ElementHandler"
  },
  "obj_viewer":[
  ],
  "finder":[
  ]
 }
]